Metadata-Version: 2.1
Name: mongoengine_goodjson_v2
Version: 2.0.2
Summary: More human readable JSON serializer/de-serializer for MongoEngine
Home-page: https://github.com/reminerdino/mongoengine-goodjson
Author: Hiroaki Yamamoto, edited by Iman Ashoori
Author-email: imanashoorii.77@gmail.com
License: MIT
Keywords: json mongoengine mongodb
Classifier: Development Status :: 4 - Beta
Classifier: License :: OSI Approved :: MIT License
Classifier: Programming Language :: Python :: 2.7
Classifier: Programming Language :: Python :: 3.5
License-File: LICENSE.md
Requires-Dist: mongoengine
Requires-Dist: dateutils
